{
  "size": {
    "width": 2500,
    "height": 1686
  },
  "selected": true,
  "name": "main menu",
  "chatBarText": "Tap to open",
  "areas": [
    {
      "bounds": {
        "x": 0,
        "y": 0,
        "width": 833,
        "height": 843
      },
      "action": {
        "type": "postback",
        "displayText": "就醫指引",
        "data": "action=main_menu&category=instruction"
      }
    },
    {
      "bounds": {
        "x": 0,
        "y": 843,
        "width": 833,
        "height": 843
      },
      "action": {
        "type": "postback",
        "displayText": "生理記錄",
        "data": "action=main_menu&category=health_record"
      }
    },
    {
      "bounds": {
        "x": 833,
        "y": 0,
        "width": 833,
        "height": 843
      },
      "action": {
        "type": "postback",
        "displayText": "孕期衛教",
        "data": "action=main_menu&category=health_education"
      }
    },
    {
      "bounds": {
        "x": 833,
        "y": 843,
        "width": 833,
        "height": 843
      },
      "action": {
        "type": "postback",
        "displayText": "好文連結",
        "data": "action=main_menu&category=articles"
      }
    },
    {
      "bounds": {
        "x": 1666,
        "y": 0,
        "width": 833,
        "height": 843
      },
      "action": {
        "type": "postback",
        "displayText": "胎兒成長",
        "data": "action=main_menu&category=fetus_growth"
      }
    },
    {
      "bounds": {
        "x": 1666,
        "y": 843,
        "width": 833,
        "height": 843
      },
      "action": {
        "type": "postback",
        "displayText": "媽媽教室",
        "data": "action=main_menu&category=mommy_class"
      }
    }
  ]
}